dazbo_commons/__init__.py
dazbo_commons/colored_logging.py
dazbo_commons/file_locations.py
dazbo_commons/read_env_file.py
dazbo_commons-0.2.0.dist-info/licenses/LICENSE
dazbo_commons-0.2.0.dist-info/METADATA
dazbo_commons-0.2.0.dist-info/WHEEL
dazbo_commons-0.2.0.dist-info/top_level.txt
dazbo_commons-0.2.0.dist-info/RECORD
