Metadata-Version: 2.4
Name: dazbo_commons
Version: 0.2.0
Summary: Handy utility code, such as coloured logging.
Author-email: Darren Lester <derailed.dash@gmail.com>
License: MIT License
Project-URL: Homepage, https://github.com/derailed-dash/dazbo-commons-py
Classifier: Development Status :: 4 - Beta
Classifier: Intended Audience :: Developers
Classifier: License :: OSI Approved :: MIT License
Classifier: Programming Language :: Python :: 3
Classifier: Programming Language :: Python :: 3.7
Requires-Python: >=3.11
License-File: LICENSE
Requires-Dist: colorama
Requires-Dist: python-dotenv
Provides-Extra: lint
Requires-Dist: ruff; extra == "lint"
Requires-Dist: mypy; extra == "lint"
Requires-Dist: codespell; extra == "lint"
Requires-Dist: types-pyyaml; extra == "lint"
Requires-Dist: types-requests; extra == "lint"
Provides-Extra: build
Requires-Dist: build; extra == "build"
Requires-Dist: twine; extra == "build"
Dynamic: license-file
